Workbook

Sheet Assumptions
A1: DeepInfer 128-GPU cost model - assumptions
A2: Yellow cells are editable; every other sheet recomputes. Numbers are public data plus the estimates in the write-up.
A5: Total GPUs | B5: 128 | C5: 64 prefill + 64 decode: the minimum efficient unit from the official Q&A
A6: Prefill GPUs | B6: 64
A7: Decode GPUs | B7: 64
A8: Rental price (USD / GPU-hour) | B8: 2.5 | C8: B200-class spot runs 2-3, on-demand 4-6; replace with your own quote
A9: Decode throughput per GPU (tokens/s) | B9: 14466 | C9: Official benchmark: EP64/DP64, 60 concurrent sequences per rank
A10: Hours per day | B10: 24
A11: Days per month | B11: 30
A12: Official revenue benchmark (USD / GPU-hour) | B12: 38 | C12: Official Q&A: revenue per GPU-hour at off-peak pricing (revenue, not profit)
A13: Official cluster volume (tokens / day) | B13: 155000000000000 | C13: 155 trillion tokens per day
A14: KV cache per GPU (TB, logical) | B14: 14.4 | C14: Official: about 14.4 TB per GPU, logical
A15: 3FS erasure-coding overhead | B15: 1.2 | C15: 10+2 erasure coding: physical = logical x 1.2
A16: Usable capacity per storage server (TB) | B16: 614.6 | C16: 20 x 30.73 TB SSDs

Sheet Cost model
A1: Cost model
A2: Change the yellow cells on the Assumptions sheet; this sheet follows.
A4: Throughput and cost
A5: Metric | B5: Value | C5: Unit | D5: Notes
A6: Total throughput (full load) | B6: =Assumptions!$B$5*Assumptions!$B$9 -> 0 | C6: tokens/s | D6: GPU count x per-GPU throughput
A7: Daily output (full load) | B7: =Assumptions!$B$5*Assumptions!$B$9*Assumptions!$B$10*3600 -> 0 | C7: tokens/day | D7: about 160 billion
A8: Cost per million tokens (full load) | B8: =Assumptions!$B$5*Assumptions!$B$8/(Assumptions!$B$5*Assumptions!$B$9*3600/1000000) -> 0 | C8: $/M tokens | D8: =128 x price / tokens per hour -> 0
A9: Rental cost per hour | B9: =Assumptions!$B$5*Assumptions!$B$8 -> 0 | C9: USD/hour
A10: Rental cost per day | B10: =Assumptions!$B$5*Assumptions!$B$8*Assumptions!$B$10 -> 0 | C10: USD/day
A11: Rental cost per month | B11: =Assumptions!$B$5*Assumptions!$B$8*Assumptions!$B$10*Assumptions!$B$11 -> 0 | C11: USD/month | D11: excludes storage, network and staff
A12: One-week trial | B12: =Assumptions!$B$5*Assumptions!$B$8*Assumptions!$B$10*7 -> 0 | C12: USD | D12: the entry ticket for a single validation run
A14: Derived from the official revenue benchmark
A15: Revenue at full load (128 GPUs) | B15: =Assumptions!$B$5*Assumptions!$B$12 -> 0 | C15: USD/hour | D15: official figure: 38 USD per GPU-hour
A16: Implied price | B16: =Assumptions!$B$5*Assumptions!$B$12/(Assumptions!$B$5*Assumptions!$B$9*3600/1000000) -> 0 | C16: $/M tokens | D16: blended; no input/output split, excludes storage
A17: Break-even utilisation | B17: =Assumptions!$B$8/Assumptions!$B$12 -> 0 | D17: =rental price / 38; below this you lose money -> 0
A19: Utilisation sensitivity (cost per million tokens)
A20: Utilisation | B20: Cost $/M | C20: Daily output (tokens)
A21: 1 | B21: =Assumptions!$B$5*Assumptions!$B$8/(Assumptions!$B$5*Assumptions!$B$9*3600*1.0/1000000) -> 0 | C21: =Assumptions!$B$5*Assumptions!$B$9*Assumptions!$B$10*3600*1.0 -> 0
A22: 0.8 | B22: =Assumptions!$B$5*Assumptions!$B$8/(Assumptions!$B$5*Assumptions!$B$9*3600*0.8/1000000) -> 0 | C22: =Assumptions!$B$5*Assumptions!$B$9*Assumptions!$B$10*3600*0.8 -> 0
A23: 0.6 | B23: =Assumptions!$B$5*Assumptions!$B$8/(Assumptions!$B$5*Assumptions!$B$9*3600*0.6/1000000) -> 0 | C23: =Assumptions!$B$5*Assumptions!$B$9*Assumptions!$B$10*3600*0.6 -> 0
A24: 0.5 | B24: =Assumptions!$B$5*Assumptions!$B$8/(Assumptions!$B$5*Assumptions!$B$9*3600*0.5/1000000) -> 0 | C24: =Assumptions!$B$5*Assumptions!$B$9*Assumptions!$B$10*3600*0.5 -> 0
A25: 0.3 | B25: =Assumptions!$B$5*Assumptions!$B$8/(Assumptions!$B$5*Assumptions!$B$9*3600*0.3/1000000) -> 0 | C25: =Assumptions!$B$5*Assumptions!$B$9*Assumptions!$B$10*3600*0.3 -> 0
A26: 0.2 | B26: =Assumptions!$B$5*Assumptions!$B$8/(Assumptions!$B$5*Assumptions!$B$9*3600*0.2/1000000) -> 0 | C26: =Assumptions!$B$5*Assumptions!$B$9*Assumptions!$B$10*3600*0.2 -> 0
A27: 0.1 | B27: =Assumptions!$B$5*Assumptions!$B$8/(Assumptions!$B$5*Assumptions!$B$9*3600*0.1/1000000) -> 0 | C27: =Assumptions!$B$5*Assumptions!$B$9*Assumptions!$B$10*3600*0.1 -> 0
A28: 0.066 | B28: =Assumptions!$B$5*Assumptions!$B$8/(Assumptions!$B$5*Assumptions!$B$9*3600*0.066/1000000) -> 0 | C28: =Assumptions!$B$5*Assumptions!$B$9*Assumptions!$B$10*3600*0.066 -> 0
A30: Storage and scale
A31: KV cache, logical | B31: =Assumptions!$B$5*Assumptions!$B$14/1000 -> 0 | C31: PB | D31: 14.4 TB per GPU x GPU count
A32: KV cache, physical | B32: =Assumptions!$B$5*Assumptions!$B$14/1000*Assumptions!$B$15 -> 0 | C32: PB | D32: after 10+2 erasure coding
A33: Storage servers | B33: =ROUNDUP(Assumptions!$B$5*Assumptions!$B$14/1000*Assumptions!$B$15*1000/Assumptions!$B$16,0) -> 0 | C33: servers | D33: each with 20 x 30.73 TB
A34: Equivalent 128-GPU units | B34: =Assumptions!$B$13/(Assumptions!$B$5*Assumptions!$B$9*Assumptions!$B$10*3600) -> 0 | C34: units | D34: 155T/day divided by one unit's daily output; arithmetic only
A35: Implied total GPUs | B35: =Assumptions!$B$13/(Assumptions!$B$5*Assumptions!$B$9*Assumptions!$B$10*3600)*Assumptions!$B$5 -> 0 | C35: GPUs | D35: about 120,000; derived, not disclosed
A37: Estimates only, for order-of-magnitude reasoning, not procurement. Throughput comes from the official benchmark at 60 concurrent sequences per rank; a real deployment loses some of it to prefill, cache misses and request long tails.
